deepdiver_cli/__init__.py
deepdiver_cli/_legacy_session.py
deepdiver_cli/app/__init__.py
deepdiver_cli/app/app.py
deepdiver_cli/app/processor.py
deepdiver_cli/chat/__init__.py
deepdiver_cli/chat/chat_model.py
deepdiver_cli/chat/chat_provider.py
deepdiver_cli/chat/chat_provider_factory.py
deepdiver_cli/chat/exceptions.py
deepdiver_cli/chat/response_types.py
deepdiver_cli/chat/transformer.py
deepdiver_cli/cli.py
deepdiver_cli/config.py
deepdiver_cli/config_templates/config.toml
deepdiver_cli/config_templates/knowledge_config.toml
deepdiver_cli/logger.py
deepdiver_cli/plugin.py
deepdiver_cli/plugins/__init__.py
deepdiver_cli/plugins/datafilter.py
deepdiver_cli/plugins/datamask.py
deepdiver_cli/plugins/descyptor.py
deepdiver_cli/prompt/code_analyzer.md
deepdiver_cli/prompt/deepdiver.md
deepdiver_cli/prompt/inspector.md
deepdiver_cli/prompt/review_template.md
deepdiver_cli/prompt/reviewer.md
deepdiver_cli/providers/__init__.py
deepdiver_cli/providers/alibaba_provider.py
deepdiver_cli/providers/base_provider.py
deepdiver_cli/providers/deepseek_provider.py
deepdiver_cli/providers/openrouter_provider.py
deepdiver_cli/react_core/__init__.py
deepdiver_cli/react_core/agent.py
deepdiver_cli/react_core/llm.py
deepdiver_cli/react_core/prompt.py
deepdiver_cli/react_core/tool.py
deepdiver_cli/session/__init__.py
deepdiver_cli/session/exceptions.py
deepdiver_cli/session/factory.py
deepdiver_cli/session/filesystem_repository.py
deepdiver_cli/session/manager.py
deepdiver_cli/session/models.py
deepdiver_cli/session/repository.py
deepdiver_cli/session/session.py
deepdiver_cli/task.py
deepdiver_cli/tools/__init__.py
deepdiver_cli/tools/analyze_code.md
deepdiver_cli/tools/analyze_code.py
deepdiver_cli/tools/analyze_code_impl.py
deepdiver_cli/tools/ask_human.py
deepdiver_cli/tools/finish.py
deepdiver_cli/tools/glob.py
deepdiver_cli/tools/grep.py
deepdiver_cli/tools/inspect.py
deepdiver_cli/tools/load_knowledge.py
deepdiver_cli/tools/process_file.py
deepdiver_cli/tools/read.py
deepdiver_cli-0.1.0.dist-info/WHEEL
deepdiver_cli-0.1.0.dist-info/entry_points.txt
deepdiver_cli-0.1.0.dist-info/METADATA
deepdiver_cli-0.1.0.dist-info/RECORD
