Metadata-Version: 2.3
Name: deepdiver-cli
Version: 0.1.0
Summary: SWEDeepDiver is an automated analysis agent for Software Engineering (SWE) problems.
Keywords: software-engineering,debugging,analysis,agent,react,llm
Author: Steve Yang
Author-email: Steve Yang <steve.yang92@gmail.com>
License: MIT License
Classifier: Development Status :: 4 - Beta
Classifier: Intended Audience :: Developers
Classifier: Topic :: Software Development :: Debuggers
Classifier: Topic :: Software Development :: Quality Assurance
Classifier: License :: OSI Approved :: MIT License
Classifier: Programming Language :: Python :: 3
Classifier: Programming Language :: Python :: 3.12
Classifier: Programming Language :: Python :: 3.13
Requires-Dist: openai>=1.40.0
Requires-Dist: pydantic~=2.7
Requires-Dist: httpx~=0.27
Requires-Dist: tenacity~=8.2
Requires-Dist: structlog~=24.0
Requires-Dist: typer==0.21.0
Requires-Dist: pycryptodome==3.22.0
Requires-Dist: pytest>=8.0.0 ; extra == 'dev'
Requires-Dist: pytest-cov>=4.1.0 ; extra == 'dev'
Requires-Dist: black>=24.0.0 ; extra == 'dev'
Requires-Dist: isort>=5.13.0 ; extra == 'dev'
Requires-Dist: flake8>=7.0.0 ; extra == 'dev'
Requires-Dist: mypy>=1.8.0 ; extra == 'dev'
Requires-Dist: pre-commit>=3.6.0 ; extra == 'dev'
Maintainer: Steve Yang
Maintainer-email: Steve Yang <steve.yang92@gmail.com>
Requires-Python: >=3.12
Project-URL: Homepage, https://github.com/SteveYang92/SWEDeepDiver
Project-URL: Documentation, https://github.com/SteveYang92/SWEDeepDiver#readme
Project-URL: Repository, https://github.com/SteveYang92/SWEDeepDiver.git
Project-URL: Issues, https://github.com/SteveYang92/SWEDeepDiver/issues
Project-URL: Changelog, https://github.com/SteveYang92/SWEDeepDiver/releases
Provides-Extra: dev
